pyzayo/__init__.py
pyzayo/api.py
pyzayo/base_client.py
pyzayo/client.py
pyzayo/consts.py
pyzayo/mtc_client.py
pyzayo/mtc_mixin.py
pyzayo/mtc_models.py
pyzayo/svcinv_mixin.py
pyzayo/cli/__init__.py
pyzayo/cli/__main__.py
pyzayo/cli/cli_cases.py
pyzayo/cli/cli_mtc.py
pyzayo/cli/cli_root.py
pyzayo/cli/cli_services.py
pyzayo/cli/cli_svcinv.py
pyzayo-0.5.0.dist-info/LICENSE
pyzayo-0.5.0.dist-info/METADATA
pyzayo-0.5.0.dist-info/WHEEL
pyzayo-0.5.0.dist-info/entry_points.txt
pyzayo-0.5.0.dist-info/top_level.txt
pyzayo-0.5.0.dist-info/RECORD
