Metadata-Version: 2.1
Name: pyzayo
Version: 0.5.0
Summary: Zayo API python client
Home-page: UNKNOWN
Author: Jeremy Schulman
License: UNKNOWN
Platform: UNKNOWN
Classifier: Development Status :: 3 - Alpha
Classifier: Intended Audience :: Developers
Classifier: Intended Audience :: Customer Service
Classifier: Intended Audience :: Information Technology
Classifier: Programming Language :: Python :: 3.8
Classifier: Topic :: Software Development :: Libraries :: Python Modules
Classifier: Topic :: System :: Networking
Classifier: License :: OSI Approved :: Apache Software License
Requires-Dist: httpx
Requires-Dist: pydantic
Requires-Dist: tenacity
Requires-Dist: click
Requires-Dist: rich
Requires-Dist: first
Requires-Dist: maya
